{"constraints": [{"template": "Succession", "parameters": [["Take in charge ticket"], [" Wait"]], "support": 1, "confidence": 1, "interestFactor": 1}, {"template": "AlternateSuccession", "parameters": [["Take in charge ticket"], [" Wait"]], "support": 1, "confidence": 1, "interestFactor": 1}, {"template": "ChainSuccession", "parameters": [["Take in charge ticket"], [" Wait"]], "support": 1, "confidence": 1, "interestFactor": 1}, {"template": "AlternateSuccession", "parameters": [["Wait"], [" Closed"]], "support": 1, "confidence": 1, "interestFactor": 1}, {"template": "AlternateSuccession", "parameters": [["Wait"], [" Resolve ticket"]], "support": 1, "confidence": 1, "interestFactor": 1}, {"template": "AlternateSuccession", "parameters": [["Assign seriousness"], [" Wait"]], "support": 1, "confidence": 1, "interestFactor": 1}]}