{"constraints": [{"template": "AlternateResponse", "parameters": [["Assign seriousness"], [" Take in charge ticket"]], "support": 1, "confidence": 1, "interestFactor": 1}, {"template": "ChainResponse", "parameters": [["Assign seriousness"], [" Take in charge ticket"]], "support": 1, "confidence": 1, "interestFactor": 1}, {"template": "AlternateSuccession", "parameters": [["Take in charge ticket"], [" Closed"]], "support": 1, "confidence": 1, "interestFactor": 1}, {"template": "AlternateSuccession", "parameters": [["Take in charge ticket"], [" Resolve ticket"]], "support": 1, "confidence": 1, "interestFactor": 1}, {"template": "AlternatePrecedence", "parameters": [["Take in charge ticket"], [" Wait"]], "support": 1, "confidence": 1, "interestFactor": 1}, {"template": "ChainPrecedence", "parameters": [["Take in charge ticket"], [" Wait"]], "support": 1, "confidence": 1, "interestFactor": 1}, {"template": "AlternateSuccession", "parameters": [["Assign seriousness"], [" Take in charge ticket"]], "support": 1, "confidence": 1, "interestFactor": 1}, {"template": "ChainSuccession", "parameters": [["Assign seriousness"], [" Take in charge ticket"]], "support": 1, "confidence": 1, "interestFactor": 1}, {"template": "AlternateResponse", "parameters": [["Take in charge ticket"], [" Closed"]], "support": 1, "confidence": 1, "interestFactor": 1}, {"template": "AtMostOne", "parameters": [["Take in charge ticket"]], "support": 1, "confidence": 1, "interestFactor": 1}, {"template": "AlternateResponse", "parameters": [["Take in charge ticket"], [" Resolve ticket"]], "support": 1, "confidence": 1, "interestFactor": 1}, {"template": "AlternatePrecedence", "parameters": [["Assign seriousness"], [" Take in charge ticket"]], "support": 1, "confidence": 1, "interestFactor": 1}, {"template": "ChainPrecedence", "parameters": [["Assign seriousness"], [" Take in charge ticket"]], "support": 1, "confidence": 1, "interestFactor": 1}, {"template": "AlternatePrecedence", "parameters": [["Assign seriousness"], [" Wait"]], "support": 1, "confidence": 1, "interestFactor": 1}]}