{"constraints": [{"template": "Precedence", "parameters": [["Assign seriousness"], [" VERIFIED"]], "support": 1, "confidence": 1, "interestFactor": 1}, {"template": "AlternatePrecedence", "parameters": [["Assign seriousness"], [" VERIFIED"]], "support": 1, "confidence": 1, "interestFactor": 1}, {"template": "Precedence", "parameters": [["Take in charge ticket"], [" VERIFIED"]], "support": 1, "confidence": 1, "interestFactor": 1}, {"template": "AlternatePrecedence", "parameters": [["Take in charge ticket"], [" VERIFIED"]], "support": 1, "confidence": 1, "interestFactor": 1}]}